titan/__init__.py
titan/orbit.py
titan/cli/__init__.py
titan/cli/orbit.py
titan_moon-0.2.0.dist-info/LICENSE.md
titan_moon-0.2.0.dist-info/METADATA
titan_moon-0.2.0.dist-info/WHEEL
titan_moon-0.2.0.dist-info/entry_points.txt
titan_moon-0.2.0.dist-info/top_level.txt
titan_moon-0.2.0.dist-info/RECORD
